proofs/__init__.py
proofs/_modidx.py
proofs/assistant.py
proofs/core.py
proofs/polynomials.py
proofs-0.0.3.dist-info/LICENSE
proofs-0.0.3.dist-info/METADATA
proofs-0.0.3.dist-info/WHEEL
proofs-0.0.3.dist-info/entry_points.txt
proofs-0.0.3.dist-info/top_level.txt
proofs-0.0.3.dist-info/RECORD
